{"ean":"8719817176267","name":{"nl":"Markeerstift spuit roze","en":"Highlighter pink spray","de":"Textmarker rosa Spray"},"slug":{"nl":"/c/stiften/tutti-frutti/8719817176267/markeerstift-spuit-roze","en":"/en/c/pens/tutti-frutti/8719817176267/highlighter-pink-spray","de":"/de/c/stifte/tutti-frutti/8719817176267/textmarker-rosa-spray"},"description":{"nl":"Tutti Frutti markeerstift\r\n\r\nDeze injectiespuit maakt het markeren een stuk spannender.\r\n\r\n- Kleur: roze","en":"Tutti Frutti highlighter \r\n\r\nThis syringe is highlighting a lot more exciting. \r\n\r\n- Colour: Pink","de":"Tutti Frutti Textmarker \r\n\r\nDiese Spritze wird Hervorhebung viel spannender. \r\n\r\n- Farbe: Rosa"},"brand":{"name":"Tutti Frutti","description":null,"active":true,"logo":null,"createdAt":1651083128704,"updatedAt":1651083128704},"vendorPrice":0.95,"sellingPrice":4.95,"catalogPrice":2.6014999999999997,"sellingPriceMin":null,"active":true,"featured":false,"hasVariants":false,"reviewPending":true,"categories":[{"code":"stiften","name":{"nl":"Stiften","en":"Pens","de":"Stifte"},"slug":{"nl":"/c/stiften","en":"/en/c/pens","de":"/de/c/stifte"},"googleCategory":null,"parentCategory":"knutselen","indexable":true,"active":true,"icon":null,"facets":null,"createdAt":1651083141573,"updatedAt":1651083141573}],"variantOptions":null,"stock":[{"id":"62698785cc894a29b4f4a659","location":"TWM","quantity":2,"updatedAt":1651083141575}],"images":[{"url":"https://www.twm-bv.com/producten/original/tutti_frutti_markeerstift_spuit_roze_118762.jpg"}],"attributes":[{"type":{"code":"age","name":{"nl":"Leeftijd","en":"Age","de":"Alter"},"postfix":null,"variable":true,"facet":true},"value":{"nl":"2-4 Jaar, 4-6 Jaar","en":"2-4 Years, 4-6 Years","de":"2-4 Jahr, 4-6 Jahr"},"variants":null,"active":true},{"type":{"code":"number-of-pieces-in-package","name":{"nl":"Aantal in verpakking","en":"Number of pieces in package","de":"Stückzahl in der Verpackung"},"postfix":null,"variable":true,"facet":true},"value":{"nl":"1 Stuks","en":"1 pieces","de":"1 Stück"},"variants":null,"active":true},{"type":{"code":"colour","name":{"nl":"Kleur","en":"Colour","de":"Farbe"},"postfix":null,"variable":true,"facet":true},"value":{"nl":"Roze","en":"Pink","de":"Rosa"},"variants":null,"active":true}],"createdAt":1651083141575,"lastImportedAt":1651083141575,"updatedAt":1651083141575,"source":"TWM","sourceId":"118762","shippingSize":"XS"}